Workbook
Name YesNo: Lists!$A$2:$A$3
Name ContractType: Lists!$B$2:$B$7
Name Period: Lists!$C$2:$C$5
Name ODCCategory: Lists!$D$2:$D$7
Name DL_BY: 'Direct Labor'!$F$17
Name DL_OY1: 'Direct Labor'!$I$17
Name DL_OY2: 'Direct Labor'!$L$17
Name DL_TOTAL: 'Direct Labor'!$N$17
Name ODC_BY: 'Other Direct Costs'!$F$15
Name ODC_OY1: 'Other Direct Costs'!$G$15
Name ODC_OY2: 'Other Direct Costs'!$H$15
Name ODC_TOTAL: 'Other Direct Costs'!$I$15
Name RATE_FRINGE_BY: 'Indirect Rates'!$B$6
Name RATE_FRINGE_OY1: 'Indirect Rates'!$C$6
Name RATE_FRINGE_OY2: 'Indirect Rates'!$D$6
Name RATE_OH_BY: 'Indirect Rates'!$B$7
Name RATE_OH_OY1: 'Indirect Rates'!$C$7
Name RATE_OH_OY2: 'Indirect Rates'!$D$7
Name RATE_GA_BY: 'Indirect Rates'!$B$8
Name TCBF_BY: 'Indirect Rates'!$B$17
Name TCBF_OY1: 'Indirect Rates'!$C$17
Name TCBF_OY2: 'Indirect Rates'!$D$17
Name TCBF_TOTAL: 'Indirect Rates'!$E$17
Name FEE_RATE: Fee!$B$5
Name FEE_BY: Fee!$B$6
Name FEE_OY1: Fee!$C$6
Name FEE_OY2: Fee!$D$6
Name FEE_TOTAL: Fee!$E$6
Name PRICE_BY: Fee!$B$7
Name PRICE_OY1: Fee!$C$7
Name PRICE_OY2: Fee!$D$7
Name PRICE_TOTAL: Fee!$E$7

Sheet Lists
A1: Yes / No | B1: Contract Type | C1: Period | D1: ODC Category
A2: Yes | B2: FFP | C2: Base Year | D2: Travel
A3: No | B3: FFP-LOE | C3: Option Year 1 | D3: Other Direct Costs
B4: T&M | C4: Option Year 2 | D4: Subcontracts
B5: CPFF | C5: All Periods | D5: Materials
B6: CPIF | D6: Equipment
B7: IDIQ | D7: Other

Sheet Direct Labor
A1: DIRECT LABOR COST ESTIMATE
A2: Contract: Professional Services Support — Agency: Department of Health and Human Services (HHS/ASFR) — NAICS 541611
B4: Solicitation # | C4: HHS-2026-ASFR-0042 | H4: Contract Type | I4: FFP
B5: Contractor | C5: Acme Advisory Group LLC | H5: Set-Aside | I5: Small Business
B6: Period of Performance | C6: 24 months (base) + 2×12-month option years | H6: Contracting Office | I6: HHS / OASAM
B7: Place of Performance | C7: Washington, DC (hybrid — on-site 2 days/wk) | H7: FAR Part | I7: FAR 15.404 (Structured Fee)
B8: Submitted | C8: 2026-06-09 | H8: Rev | I8: v1.0
A10: ⚑ Escalation: OY1 rates = BY × 1.03 | OY2 rates = BY × 1.0609 (3% COLA per FAR 52.215-14) | Hours are fixed across all periods for this FFP vehicle
D12: BASE YEAR (BY) — Months 1-24 | G12: OPTION YEAR 1 (OY1) — Months 25-36 | J12: OPTION YEAR 2 (OY2) — Months 37-48 | M12: CONTRACT TOTAL
A13: # | B13: Labor Category / Position | C13: Grade / Level | D13: Hours | E13: Loaded Rate ($/hr) | F13: Cost | G13: Hours | H13: Loaded Rate ($/hr) | I13: Cost | J13: Hours | K13: Loaded Rate ($/hr) | L13: Cost | M13: Total Hours | N13: Total Cost
A14: 1 | B14: Senior Management Consultant | C14: Level III (GS-14 equiv) | D14: 1040 | E14: 145 | F14: =D14*E14 | G14: =D14 | H14: =E14*1.03 | I14: =G14*H14 | J14: =D14 | K14: =E14*1.0609 | L14: =J14*K14 | M14: =D14+G14+J14 | N14: =F14+I14+L14
A15: 2 | B15: Business Process Analyst | C15: Level II (GS-12 equiv) | D15: 2080 | E15: 98.5 | F15: =D15*E15 | G15: =D15 | H15: =E15*1.03 | I15: =G15*H15 | J15: =D15 | K15: =E15*1.0609 | L15: =J15*K15 | M15: =D15+G15+J15 | N15: =F15+I15+L15
A16: 3 | B16: Administrative Support Specialist | C16: Level I (GS-7 equiv) | D16: 520 | E16: 62 | F16: =D16*E16 | G16: =D16 | H16: =E16*1.03 | I16: =G16*H16 | J16: =D16 | K16: =E16*1.0609 | L16: =J16*K16 | M16: =D16+G16+J16 | N16: =F16+I16+L16
A17: SUBTOTAL — DIRECT LABOR | D17: =SUM(D14:D16) | F17: =SUM(F14:F16) | G17: =SUM(G14:G16) | I17: =SUM(I14:I16) | J17: =SUM(J14:J16) | L17: =SUM(L14:L16) | M17: =SUM(M14:M16) | N17: =SUM(N14:N16)
A18: Note: Rates are "fully loaded" — base salary + fringe (34%) + overhead (62%) wrapped into a single $/hr figure per FAR 31.201-2 cost allowability. Rates do NOT include G&A or fee — those are applied on Indirect Rates tab.
A20: CapturePilot Federal Lead Kit - capturepilot.com - 08 Price-to-Win Toolkit

Sheet Other Direct Costs
A1: OTHER DIRECT COSTS (ODCs)
B4: NOTE: | C4: ODCs are direct charges not attributable to labor. They must be specifically identified and justified per FAR 31.202. Each line below ties to a specific SOW task or deliverable.
B5: Travel policy: | C5: Government travel rate per GSA per diem schedule (FY 2026). DC hotel cap $258/night. M&IE $79/day. Airfare coach class only per FAR 31.205-46.
F7: BASE YEAR | G7: OPTION YEAR 1 | H7: OPTION YEAR 2 | I7: CONTRACT TOTAL
A8: # | B8: Item Description | C8: Category | D8: Qty / Trips | E8: Unit Cost | F8: BY Cost | G8: OY1 Cost | H8: OY2 Cost | I8: Total | J8: Justification / Reference
A9: 1 | B9: Quarterly kick-off and progress review meetings (airfare + hotel + M&IE) | C9: Travel | D9: 4 | E9: 650 | F9: =D9*E9 | G9: =D9*E9*1 | H9: =D9*E9*1 | I9: =F9+G9+H9 | J9: 4 trips × contractor + COR at each. GSA per diem BWI-IAD corridor. FAR 31.205-46 coach class.
A10: 2 | B10: Site visit to HHS program office (local day trip) | C10: Travel | D10: 8 | E10: 45 | F10: =D10*E10 | G10: =D10*E10*1 | H10: =D10*E10*1 | I10: =F10+G10+H10 | J10: Metro SmarTrip $4.60 each way × 8 visits BY. OY = same frequency.
A11: 3 | B11: Software licenses — MS Project Professional (annual) | C11: Other Direct Costs | D11: 3 | E11: 560 | F11: =D11*E11 | G11: =D11*E11*1.03 | H11: =D11*E11*1.0609 | I11: =F11+G11+H11 | J11: 3 licenses × project manager + 2 analysts. Vendor quote #QPR-2026-0412 on file.
A12: 4 | B12: SharePoint / O365 per-user (annual, contractor-provided) | C12: Other Direct Costs | D12: 3 | E12: 360 | F12: =D12*E12 | G12: =D12*E12*1.03 | H12: =D12*E12*1.0609 | I12: =F12+G12+H12 | J12: 3 seats × $120/user/yr. GFE not available for contractors on this task.
A13: 5 | B13: Printed deliverables and binders for 4 quarterly reports | C13: Materials | D13: 4 | E13: 120 | F13: =D13*E13 | G13: =D13*E13*1 | H13: =D13*E13*1 | I13: =F13+G13+H13 | J13: 4 reports × 10 copies each. Agency requires physical binder per CDRL A001.
A14: 6 | B14: Professional publications and reference databases | C14: Other Direct Costs | D14: 1 | E14: 950 | F14: =D14*E14 | G14: =D14*E14*1 | H14: =D14*E14*1 | I14: =F14+G14+H14 | J14: Federal Register archive access. One annual subscription covers all staff.
A15: SUBTOTAL — OTHER DIRECT COSTS | F15: =SUM(F9:F14) | G15: =SUM(G9:G14) | H15: =SUM(H9:H14) | I15: =SUM(I9:I14)
A17: CapturePilot Federal Lead Kit - capturepilot.com - 08 Price-to-Win Toolkit

Sheet Indirect Rates
A1: INDIRECT RATES & COST BUILDUP
A2: Rates based on most recent DCAA-audited forward pricing rate agreement (FPRA). Final negotiated rates will govern per FAR 42.703. All pools applied to direct labor only (ODCs are not a G&A base on this contract structure).
A4: RATE DEFINITIONS (edit these cells — formulas below will update automatically)
A5: Indirect Pool | B5: BY Rate | C5: OY1 Rate | D5: OY2 Rate | E5: Base | F5: FAR Reference / Audit Authority
A6: Fringe Benefits | B6: 0.34 | C6: 0.35 | D6: 0.36 | E6: Direct Labor | F6: FAR 31.205-6(m). DCAA audit report #2025-001. Covers FICA, medical, dental, vision, 401(k) match, PTO, holidays.
A7: Overhead (Facilities) | B7: 0.62 | C7: 0.63 | D7: 0.64 | E7: Direct Labor + Fringe | F7: FAR 31.203. Pools indirect facilities costs: rent, utilities, IT infrastructure, equipment depreciation.
A8: G&A (General & Admin) | B8: 0.15 | C8: 0.15 | D8: 0.15 | E8: Total Cost Input (TCI) | F8: FAR 31.203(d). Applied to TCI (DL + fringe + OH + ODC) — captures executive salaries, accounting, BD costs.
A10: COST BUILDUP BY PERIOD (all formulas reference Direct Labor and ODC named ranges)
A11: Cost Element | B11: Base Year | C11: Option Year 1 | D11: Option Year 2 | E11: Contract Total | F11: Notes
A12: Direct Labor | B12: =DL_BY | C12: =DL_OY1 | D12: =DL_OY2 | E12: =B12+C12+D12 | F12: From Direct Labor tab — SUMPRODUCT of hours × fully-loaded rate per labor category
A13: Fringe Benefits | B13: =B12*RATE_FRINGE_BY | C13: =C12*RATE_FRINGE_OY1 | D13: =D12*RATE_FRINGE_OY2 | E13: =B13+C13+D13 | F13: DL × fringe rate (B6/C6/D6). FAR 31.205-6(m).
A14: Overhead | B14: =(B12+B13)*RATE_OH_BY | C14: =(C12+C13)*RATE_OH_OY1 | D14: =(D12+D13)*RATE_OH_OY2 | E14: =B14+C14+D14 | F14: (DL + Fringe) × overhead rate. Pool covers facilities, IT, equipment.
A15: Other Direct Costs | B15: =ODC_BY | C15: =ODC_OY1 | D15: =ODC_OY2 | E15: =B15+C15+D15 | F15: From ODC tab — travel, software, materials. All individually justified.
A16: G&A (applied to TCI) | B16: =(B12+B13+B14+B15)*RATE_GA_BY | C16: =(C12+C13+C14+C15)*RATE_GA_BY | D16: =(D12+D13+D14+D15)*RATE_GA_BY | E16: =B16+C16+D16 | F16: G&A rate (8) × Total Cost Input (DL+Fringe+OH+ODC). FAR 31.203(d).
A17: TOTAL COST BEFORE FEE | B17: =SUM(B12:B16) | C17: =SUM(C12:C16) | D17: =SUM(D12:D16) | E17: =SUM(E12:E16)
A19: CapturePilot Federal Lead Kit - capturepilot.com - 08 Price-to-Win Toolkit

Sheet Fee
A1: FEE COMPUTATION — 8% FIXED FEE
A2: Fixed fee (profit) applied at 8% of total estimated cost (DL + indirect costs). Per DFARS 215.404-4, DoD weighted guidelines suggest 8-10% for low-risk FFP professional services. DCAA will not audit fee — it's negotiated, not cost-justified.
A4: Fee Element | B4: Base Year | C4: Option Year 1 | D4: Option Year 2 | E4: Contract Total | F4: Notes
A5: Fee Rate (edit to adjust) | B5: 0.08 | C5: =B5 | D5: =B5 | F5: Edit column B only. OY1 and OY2 inherit same rate. Defensible range for FFP professional services: 7-12% (DFARS 215.404-4).
A6: Fee Amount (TCBF × Fee Rate) | B6: =TCBF_BY*FEE_RATE | C6: =TCBF_OY1*FEE_RATE | D6: =TCBF_OY2*FEE_RATE | E6: =B6+C6+D6 | F6: Computed as TCBF (from Indirect Rates tab) × fee rate above. On FFP you lock this number at award — it doesn't float with actuals.
A7: TOTAL PROPOSED PRICE (TCBF + Fee) | B7: =TCBF_BY+FEE_BY | C7: =TCBF_OY1+FEE_OY1 | D7: =TCBF_OY2+FEE_OY2 | E7: =TCBF_TOTAL+FEE_TOTAL | F7: This is the number that goes on Section B of the SF 1449 / SF 33 and your Cover Page. Verify it's within ±5% of your PTW estimate before submitting.
A9: SANITY CHECK — Total proposed price above should be near $750,000. If it's significantly off, review your hours or rates on the Direct Labor tab.
A11: CapturePilot Federal Lead Kit - capturepilot.com - 08 Price-to-Win Toolkit

Sheet Summary
A1: COST PROPOSAL SUMMARY — SF 1411 FORMAT
A2: Professional Services Support | HHS-2026-ASFR-0042 | Acme Advisory Group LLC | 24-month base + 2 option years
A4: Cost Element | B4: Base Year | C4: Option Year 1 | D4: Option Year 2 | E4: Contract Total | F4: % of Price
A5: Direct Labor | B5: =DL_BY | C5: =DL_OY1 | D5: =DL_OY2 | E5: =DL_TOTAL | F5: =IFERROR(E5/PRICE_TOTAL,0)
A6: Fringe Benefits | B6: ='Indirect Rates'!B13 | C6: ='Indirect Rates'!C13 | D6: ='Indirect Rates'!D13 | E6: =B6+C6+D6 | F6: =IFERROR(E6/PRICE_TOTAL,0)
A7: Overhead | B7: ='Indirect Rates'!B14 | C7: ='Indirect Rates'!C14 | D7: ='Indirect Rates'!D14 | E7: =B7+C7+D7 | F7: =IFERROR(E7/PRICE_TOTAL,0)
A8: Other Direct Costs | B8: =ODC_BY | C8: =ODC_OY1 | D8: =ODC_OY2 | E8: =ODC_TOTAL | F8: =IFERROR(E8/PRICE_TOTAL,0)
A9: G&A | B9: ='Indirect Rates'!B16 | C9: ='Indirect Rates'!C16 | D9: ='Indirect Rates'!D16 | E9: =B9+C9+D9 | F9: =IFERROR(E9/PRICE_TOTAL,0)
A10: Total Cost Before Fee | B10: =TCBF_BY | C10: =TCBF_OY1 | D10: =TCBF_OY2 | E10: =TCBF_TOTAL | F10: =IFERROR(E10/PRICE_TOTAL,0)
A11: Fee (8%) | B11: =FEE_BY | C11: =FEE_OY1 | D11: =FEE_OY2 | E11: =FEE_TOTAL | F11: =IFERROR(E11/PRICE_TOTAL,0)
A12: TOTAL PROPOSED PRICE | B12: =PRICE_BY | C12: =PRICE_OY1 | D12: =PRICE_OY2 | E12: =PRICE_TOTAL | F12: 100.0%
A14: COST-SHARE REFERENCE TABLE (N/A for this FFP — shown for cost-plus reference)
A15: Scenario | B15: Gov't Share | C15: Contractor Share | D15: Gov't Dollar Amount | E15: Contractor Dollar Amount | F15: Note
A16: No cost-sharing (standard FFP) | B16: 100% | C16: 0% | D16: =PRICE_TOTAL | E16: =0 | F16: Standard FFP — contractor bears all cost risk above ceiling price.
A17: 20% contractor cost-share (SBIR Phase II) | B17: 80% | C17: 20% | D17: =PRICE_TOTAL*0.8 | E17: =PRICE_TOTAL*0.2 | F17: Common in SBIR Phase II (FAR 35.003, SBA SBIR Policy Directive §4(a)).
A18: 50/50 cost-share (R&D partnership) | B18: 50% | C18: 50% | D18: =PRICE_TOTAL*0.5 | E18: =PRICE_TOTAL*0.5 | F18: DOE and NSF sometimes require 50/50 for commercialization programs.
A20: CapturePilot Federal Lead Kit - capturepilot.com - 08 Price-to-Win Toolkit
